{
  "ok": true,
  "tick": 149,
  "policy": {
    "mutationRate": 0.2,
    "selectionPressure": 0.6,
    "explorationBias": 0.5
  },
  "reward": {
    "total": 13.91978021849968,
    "last": -0.40723923147688246,
    "smoothed": 0.019396509129057077,
    "history": [
      {
        "tick": 1,
        "reward": -0.34005160882511687
      },
      {
        "tick": 2,
        "reward": -0.790670385393804
      },
      {
        "tick": 3,
        "reward": -0.24382542481416858
      },
      {
        "tick": 4,
        "reward": -0.2375248187241924
      },
      {
        "tick": 5,
        "reward": -0.23385754854801322
      },
      {
        "tick": 6,
        "reward": -0.2584000357780931
      },
      {
        "tick": 7,
        "reward": -0.2732150597456191
      },
      {
        "tick": 8,
        "reward": 0.00008788360851491595
      },
      {
        "tick": 9,
        "reward": -0.3180947558498851
      },
      {
        "tick": 10,
        "reward": -0.006821984797698966
      },
      {
        "tick": 11,
        "reward": 0.33633537644260625
      },
      {
        "tick": 12,
        "reward": 0.04117776561792247
      },
      {
        "tick": 13,
        "reward": -0.7724937339042431
      },
      {
        "tick": 14,
        "reward": -0.21847738316629306
      },
      {
        "tick": 15,
        "reward": -0.409958741674805
      },
      {
        "tick": 16,
        "reward": 0.3806810529344976
      },
      {
        "tick": 17,
        "reward": 0.24038888478658904
      },
      {
        "tick": 18,
        "reward": 0.3905861860686275
      },
      {
        "tick": 19,
        "reward": 0.1428866813952606
      },
      {
        "tick": 20,
        "reward": 0.45222178426432413
      },
      {
        "tick": 21,
        "reward": 0.17697145461444724
      },
      {
        "tick": 22,
        "reward": -0.1562588421002632
      },
      {
        "tick": 23,
        "reward": 0.16763621701917414
      },
      {
        "tick": 24,
        "reward": -0.08959273649128874
      },
      {
        "tick": 25,
        "reward": -0.06897275183140116
      },
      {
        "tick": 26,
        "reward": 0.2584659064197004
      },
      {
        "tick": 27,
        "reward": -0.03309390497114562
      },
      {
        "tick": 28,
        "reward": -0.19513314689249156
      },
      {
        "tick": 29,
        "reward": 0.6066225298775535
      },
      {
        "tick": 30,
        "reward": 0.9356716238853945
      },
      {
        "tick": 31,
        "reward": 0.6218464018408315
      },
      {
        "tick": 32,
        "reward": 0.3393521347352028
      },
      {
        "tick": 33,
        "reward": 0.08893395429942294
      },
      {
        "tick": 34,
        "reward": 0.09442083789884935
      },
      {
        "tick": 35,
        "reward": 0.11184654825169098
      },
      {
        "tick": 36,
        "reward": 0.08939802496136272
      },
      {
        "tick": 37,
        "reward": 0.12143960698411171
      },
      {
        "tick": 38,
        "reward": 0.169429577028271
      },
      {
        "tick": 39,
        "reward": 0.16429349035196
      },
      {
        "tick": 40,
        "reward": 0.17845112139802205
      },
      {
        "tick": 41,
        "reward": -0.3021811281288414
      },
      {
        "tick": 42,
        "reward": -0.862440229289388
      },
      {
        "tick": 43,
        "reward": -0.41006549130706693
      },
      {
        "tick": 44,
        "reward": 0.42346466417156003
      },
      {
        "tick": 45,
        "reward": 0.14864193798559747
      },
      {
        "tick": 46,
        "reward": 0.18072197938064655
      },
      {
        "tick": 47,
        "reward": 0.5039229249465531
      },
      {
        "tick": 48,
        "reward": -0.2765947137692739
      },
      {
        "tick": 49,
        "reward": -0.7485756402421444
      },
      {
        "tick": 50,
        "reward": -1.2258797508168435
      },
      {
        "tick": 51,
        "reward": -0.7386197210492391
      },
      {
        "tick": 52,
        "reward": -0.2190723389331763
      },
      {
        "tick": 53,
        "reward": 0.5324986690454643
      },
      {
        "tick": 54,
        "reward": 0.21138901299049112
      },
      {
        "tick": 55,
        "reward": -0.29970802823302484
      },
      {
        "tick": 56,
        "reward": 0.19626899177646895
      },
      {
        "tick": 57,
        "reward": 0.18848418654425278
      },
      {
        "tick": 58,
        "reward": 0.44388211676613865
      },
      {
        "tick": 59,
        "reward": 0.14264221379728945
      },
      {
        "tick": 60,
        "reward": 0.16362319081207624
      },
      {
        "tick": 61,
        "reward": -0.31833344685669174
      },
      {
        "tick": 62,
        "reward": -0.8655530727213737
      },
      {
        "tick": 63,
        "reward": -0.341657410799453
      },
      {
        "tick": 64,
        "reward": 0.19707969314985682
      },
      {
        "tick": 65,
        "reward": 0.2167372017011623
      },
      {
        "tick": 66,
        "reward": 0.2444004051991215
      },
      {
        "tick": 67,
        "reward": 0.5216597439668695
      },
      {
        "tick": 68,
        "reward": 0.8470628721046751
      },
      {
        "tick": 69,
        "reward": 1.1307303649666598
      },
      {
        "tick": 70,
        "reward": 0.31439399702057114
      },
      {
        "tick": 71,
        "reward": 0.4912030061012721
      },
      {
        "tick": 72,
        "reward": -0.34440680230017334
      },
      {
        "tick": 73,
        "reward": 0.19555889973459806
      },
      {
        "tick": 74,
        "reward": 0.19777000152213847
      },
      {
        "tick": 75,
        "reward": 0.17567411347514506
      },
      {
        "tick": 76,
        "reward": -0.30132949366518574
      },
      {
        "tick": 77,
        "reward": -0.7561133900956929
      },
      {
        "tick": 78,
        "reward": -0.2590949200204005
      },
      {
        "tick": 79,
        "reward": 0.20603335218306096
      },
      {
        "tick": 80,
        "reward": 0.2378685377184223
      },
      {
        "tick": 81,
        "reward": 0.19786397111702375
      },
      {
        "tick": 82,
        "reward": 0.18826747862641224
      },
      {
        "tick": 83,
        "reward": 0.14814194191207536
      },
      {
        "tick": 84,
        "reward": 0.46862531648021255
      },
      {
        "tick": 85,
        "reward": 0.1902605874858903
      },
      {
        "tick": 86,
        "reward": 0.1741450801791104
      },
      {
        "tick": 87,
        "reward": 0.1895605084881066
      },
      {
        "tick": 88,
        "reward": 0.1830014609491252
      },
      {
        "tick": 89,
        "reward": 0.1713443189700446
      },
      {
        "tick": 90,
        "reward": 0.011412444143443945
      },
      {
        "tick": 91,
        "reward": 0.7660466472359949
      },
      {
        "tick": 92,
        "reward": 1.0121491748436546
      },
      {
        "tick": 93,
        "reward": 0.6888185017120914
      },
      {
        "tick": 94,
        "reward": -0.13991863396330578
      },
      {
        "tick": 95,
        "reward": 0.09948793520670832
      },
      {
        "tick": 96,
        "reward": 0.36043363307242793
      },
      {
        "tick": 97,
        "reward": 0.06867578728430937
      },
      {
        "tick": 98,
        "reward": 0.10173750130312545
      },
      {
        "tick": 99,
        "reward": -0.43728854808682016
      },
      {
        "tick": 100,
        "reward": 0.3697665377165281
      },
      {
        "tick": 101,
        "reward": 0.1565806832281632
      },
      {
        "tick": 102,
        "reward": 0.33628933141617623
      },
      {
        "tick": 103,
        "reward": -0.44793571223538725
      },
      {
        "tick": 104,
        "reward": 0.07625283032917476
      },
      {
        "tick": 105,
        "reward": 0.06659998497673572
      },
      {
        "tick": 106,
        "reward": 0.35521740016236414
      },
      {
        "tick": 107,
        "reward": 0.7074445008983277
      },
      {
        "tick": 108,
        "reward": 0.44547141447032884
      },
      {
        "tick": 109,
        "reward": 0.17554857975747273
      },
      {
        "tick": 110,
        "reward": 0.15607915432530184
      },
      {
        "tick": 111,
        "reward": 0.2002306096184422
      },
      {
        "tick": 112,
        "reward": 0.2359687278553146
      },
      {
        "tick": 113,
        "reward": 0.18939008912975397
      },
      {
        "tick": 114,
        "reward": 0.22063742124090147
      },
      {
        "tick": 115,
        "reward": 0.16462811732116034
      },
      {
        "tick": 116,
        "reward": 0.4365972021189346
      },
      {
        "tick": 117,
        "reward": 0.17438623485088559
      },
      {
        "tick": 118,
        "reward": 0.17998940022066826
      },
      {
        "tick": 119,
        "reward": 0.13989529116995483
      },
      {
        "tick": 120,
        "reward": 0.4530419248027726
      },
      {
        "tick": 121,
        "reward": 0.7491234330009483
      },
      {
        "tick": 122,
        "reward": 0.47842629926007685
      },
      {
        "tick": 123,
        "reward": 0.8116287115803412
      },
      {
        "tick": 124,
        "reward": -0.006847566724390353
      },
      {
        "tick": 125,
        "reward": 0.19586077264398527
      },
      {
        "tick": 126,
        "reward": -0.367482594198092
      },
      {
        "tick": 127,
        "reward": 0.41768653663075095
      },
      {
        "tick": 128,
        "reward": 0.14053315555653184
      },
      {
        "tick": 129,
        "reward": 0.10131636444797128
      },
      {
        "tick": 130,
        "reward": 0.10392678481878387
      },
      {
        "tick": 131,
        "reward": 0.0653612146144687
      },
      {
        "tick": 132,
        "reward": 0.12433498692205151
      },
      {
        "tick": 133,
        "reward": -0.41505136049520513
      },
      {
        "tick": 134,
        "reward": 0.35285872343645763
      },
      {
        "tick": 135,
        "reward": 0.7037036770306543
      },
      {
        "tick": 136,
        "reward": 0.378276247667938
      },
      {
        "tick": 137,
        "reward": 0.11362608726036187
      },
      {
        "tick": 138,
        "reward": 0.15707064803095677
      },
      {
        "tick": 139,
        "reward": -0.2927136264217528
      },
      {
        "tick": 140,
        "reward": 0.17844146021576573
      },
      {
        "tick": 141,
        "reward": 0.15508234656187364
      },
      {
        "tick": 142,
        "reward": 0.4707426060061959
      },
      {
        "tick": 143,
        "reward": -0.3529178775875497
      },
      {
        "tick": 144,
        "reward": -0.8292566340991293
      },
      {
        "tick": 145,
        "reward": -0.2996537241687279
      },
      {
        "tick": 146,
        "reward": 0.13695462301065237
      },
      {
        "tick": 147,
        "reward": 0.10958010229099108
      },
      {
        "tick": 148,
        "reward": 0.4067745423421131
      },
      {
        "tick": 149,
        "reward": -0.40723923147688246
      }
    ]
  },
  "world": {
    "entropy": 0.27361961573844124,
    "wars": 1,
    "entities": 504,
    "alliances": 0,
    "tick": 149
  },
  "evolutionaryBrain": {
    "generation": 3,
    "population": 19,
    "leader": null,
    "leaderFitness": 0.17645570674052571,
    "speciesCount": 1,
    "agents": []
  }
}